[
  {
    "file": "docs/finance/billing_policy.md",
    "department": "finance",
    "chunks": 2
  },
  {
    "file": "docs/finance/q4_finance_summary.md",
    "department": "finance",
    "chunks": 1
  },
  {
    "file": "docs/general/business_glossary.md",
    "department": "general",
    "chunks": 2
  },
  {
    "file": "docs/general/company_overview.md",
    "department": "general",
    "chunks": 1
  },
  {
    "file": "docs/general/data_dictionary.md",
    "department": "general",
    "chunks": 2
  },
  {
    "file": "docs/hr/compliance_training.md",
    "department": "hr",
    "chunks": 1
  },
  {
    "file": "docs/hr/hr_policy_handbook.md",
    "department": "hr",
    "chunks": 2
  },
  {
    "file": "docs/ops/operations_runbook.md",
    "department": "ops",
    "chunks": 1
  },
  {
    "file": "docs/product/product_catalog.md",
    "department": "product",
    "chunks": 1
  },
  {
    "file": "docs/support/support_playbook.md",
    "department": "support",
    "chunks": 1
  }
]